{
  "hero": {
    "video": "/media/reel.mp4",
    "poster": "/media/IMAGE1.jpg"
  },
  "statement": [
    {
      "text": "I strive to be at the forefront of creativity and innovation.",
      "image": "/media/IMAGE1.jpg",
      "align": "left"
    },
    {
      "text": "To create culturally-relevant, thought-provoking activations that WOW an audience.",
      "image": "/media/IMAGE2.png",
      "align": "center"
    },
    {
      "text": "...and enhance a brand's identity.",
      "image": "/media/IMAGE3.png",
      "align": "right"
    },
    {
      "text": "This is what I do.",
      "textRight": "And I love it.",
      "image": "/media/IMAGE4.jpg",
      "align": "split"
    }
  ],
  "numbers": {
    "headline": "What over a decade of building looks like",
    "headlineHighlight": "over a decade",
    "roleLines": [
      "3× Emmy Award Winning",
      "Creative Director",
      "Producer",
      "Creative Strategist",
      "Innovator"
    ],
    "metrics": [
      {
        "value": 3,
        "label": "Emmys won",
        "style": "normal"
      },
      {
        "value": 99,
        "suffix": "M+",
        "label": "Social views",
        "style": "normal"
      },
      {
        "value": 14,
        "label": "Years of experience",
        "style": "normal"
      },
      {
        "value": 7,
        "label": "Countries I have led creative in",
        "style": "normal"
      },
      {
        "value": 0,
        "label": "Super Bowls my favorite team has won",
        "style": "normal"
      }
    ]
  },
  "whatIDo": {
    "title": "What I Do",
    "items": [
      {
        "n": "01",
        "title": "Creative Direction",
        "body": "I specialize in conceptualizing, directing, and executing high-impact creative across live shows, sports, concerts, and immersive experiences."
      },
      {
        "n": "02",
        "title": "Campaign Strategy",
        "body": "I build culturally relevant creative campaigns that extend across broadcast, social, digital, and in-person experiences."
      },
      {
        "n": "03",
        "title": "Innovation",
        "body": "I bridge creativity and emerging technology to develop innovative content, workflows, and experiences powered by AI."
      }
    ]
  },
  "contact": {
    "email": "jrestaino91@gmail.com",
    "location": "Las Vegas, NV\nWorldwide",
    "socials": [
      {
        "label": "Instagram",
        "url": "https://www.instagram.com/restainocreative/"
      },
      {
        "label": "LinkedIn",
        "url": "https://www.linkedin.com/in/justinrestaino/"
      }
    ]
  },
  "brandLogos": [
    {
      "image": "/media/RiotGames.png",
      "name": "Riot Games"
    },
    {
      "image": "/media/RedBull.png",
      "name": "Red Bull"
    },
    {
      "image": "/media/NHL.png",
      "name": "NHL"
    },
    {
      "image": "/media/NFL.png",
      "name": "NFL"
    },
    {
      "image": "/media/MasterCard.png",
      "name": "Master Card"
    },
    {
      "image": "/media/LouisVuitton.png",
      "name": "Louis Vuitton"
    },
    {
      "image": "/media/CBS.png",
      "name": "CBS"
    }
  ]
}